ports_list/__init__.py
ports_list/__main__.py
ports_list/ports.py
ports_list-0.1.0.dist-info/WHEEL
ports_list-0.1.0.dist-info/METADATA
ports_list-0.1.0.dist-info/RECORD
